{"weapons":[{"damage":500,"image":"Gamelib\\src\\image\\pistola.png","explosionRange":5,"levelMultiplier":25,"level":1,"supplies":1,"scope":5,"name":"Pistola","x":0,"levelDependant":true,"y":0,"maxSupplies":1},{"damage":100,"image":"Gamelib\\src\\image\\hacha.png","explosionRange":1,"levelMultiplier":10,"level":1,"supplies":0,"scope":2,"name":"Hacha","x":0,"levelDependant":true,"y":0,"maxSupplies":0},{"damage":500,"image":"Gamelib\\src\\image\\bomba.png","explosionRange":5,"levelMultiplier":15,"level":1,"supplies":1,"scope":5,"name":"Bomba","x":0,"levelDependant":true,"y":0,"maxSupplies":1},{"damage":230,"image":"Gamelib\\src\\image\\espada.png","explosionRange":1,"levelMultiplier":5,"level":1,"supplies":0,"scope":1,"name":"Espada","x":0,"levelDependant":true,"y":0,"maxSupplies":0},{"damage":230,"image":"Gamelib\\src\\image\\granada.png","explosionRange":1,"levelMultiplier":30,"level":1,"supplies":0,"scope":1,"name":"Granada","x":0,"levelDependant":true,"y":0,"maxSupplies":0},{"damage":230,"image":"Gamelib\\src\\image\\bomba2.png","explosionRange":1,"levelMultiplier":20,"level":1,"supplies":0,"scope":1,"name":"Bomba2","x":0,"levelDependant":true,"y":0,"maxSupplies":0},{"damage":500,"image":"Gamelib\\src\\image\\dinamita.png","explosionRange":5,"levelMultiplier":30,"level":1,"supplies":1,"scope":5,"name":"Dinamita","x":0,"levelDependant":true,"y":0,"maxSupplies":1},{"damage":100,"image":"Gamelib\\src\\image\\botiquiin.png","explosionRange":1,"levelMultiplier":25,"level":1,"supplies":0,"scope":2,"name":"Botiquiin","x":0,"levelDependant":true,"y":0,"maxSupplies":0}]}